covidslimiter/__init__.py
covidslimiter/decorator.py
covidslimiter/rate_limiter.py
covidslimiter-0.43.dist-info/METADATA
covidslimiter-0.43.dist-info/WHEEL
covidslimiter-0.43.dist-info/top_level.txt
covidslimiter-0.43.dist-info/RECORD
